df_anonymizer/__init__.py
df_anonymizer/evaluation.py
df_anonymizer/generalization.py
df_anonymizer/masking.py
df_anonymizer/perturbation.py
df_anonymizer/pseudonymization.py
df_anonymizer/shuffling.py
df_anonymizer/suppression.py
df_anonymizer-0.1.6.dist-info/licenses/LICENSE
df_anonymizer-0.1.6.dist-info/METADATA
df_anonymizer-0.1.6.dist-info/WHEEL
df_anonymizer-0.1.6.dist-info/top_level.txt
df_anonymizer-0.1.6.dist-info/RECORD
