Metadata-Version: 2.4
Name: df_anonymizer
Version: 0.1.6
Summary: A Python library for anonymizing and transforming data in pandas DataFrames, including masking, suppression, perturbation, permutation, generalization, and pseudonymization.
Author: Tan Shih Jen
License: MIT
Requires-Python: >=3.7
License-File: LICENSE
Requires-Dist: pandas<3.0.0,>=2.3.0
Requires-Dist: numpy<3.0.0,>=2.0.2
Dynamic: license-file
